stackmorelayers/__init__.py
stackmorelayers/ensemble.py
stackmorelayers/typing.py
stackmorelayers/utils.py
stackmorelayers-0.0.8.dist-info/LICENSE
stackmorelayers-0.0.8.dist-info/WHEEL
stackmorelayers-0.0.8.dist-info/METADATA
stackmorelayers-0.0.8.dist-info/RECORD
